translationrecorder
