Metadata-Version: 1.0
Name: translationrecorder
Version: 1.0.2
Summary: Records gettext translation messages and synchronizes to message catalogs.
Home-page: UNKNOWN
Author: Malthe Borch
Author-email: mborch@gmail.com
License: BSD-like (http://repoze.org/license.html)
Platform: UNKNOWN
Classifier: Development Status :: 4 - Beta
Classifier: Intended Audience :: Developers
Classifier: Programming Language :: Python
Classifier: Programming Language :: Python :: 2
Classifier: Programming Language :: Python :: 2.5
Classifier: Programming Language :: Python :: 2.6
Classifier: Programming Language :: Python :: 2.7
